passwordstrengthscore/__init__.py
passwordstrengthscore/config.py
passwordstrengthscore/core.py
passwordstrengthscore/model_loader.py
passwordstrengthscore/utils.py
passwordstrengthscore/features/__init__.py
passwordstrengthscore/features/cnn_features.py
passwordstrengthscore/features/rf_features.py
passwordstrengthscore/features/svm_features.py
passwordstrengthscore-0.1.0.dist-info/licenses/LICENSE
passwordstrengthscore-0.1.0.dist-info/METADATA
passwordstrengthscore-0.1.0.dist-info/WHEEL
passwordstrengthscore-0.1.0.dist-info/top_level.txt
passwordstrengthscore-0.1.0.dist-info/RECORD
