Metadata-Version: 2.4
Name: passwordstrengthscore
Version: 0.1.0
Summary: A machine learning-based password strength evaluation library
Home-page: 
Author: Encik Megat
Author-email: muhammed.mazelan03@s.unikl.edu.my
Classifier: Programming Language :: Python :: 3
Classifier: License :: OSI Approved :: MIT License
Classifier: Operating System :: OS Independent
Classifier: Intended Audience :: Developers
Classifier: Topic :: Security :: Cryptography
Requires-Python: >=3.7
License-File: LICENSE
Requires-Dist: scikit-learn
Requires-Dist: joblib
Dynamic: author
Dynamic: author-email
Dynamic: classifier
Dynamic: license-file
Dynamic: requires-dist
Dynamic: requires-python
Dynamic: summary
